odoo/addons/l10n_fr_account_invoice_import_simple_pdf/README.rst
odoo/addons/l10n_fr_account_invoice_import_simple_pdf/__init__.py
odoo/addons/l10n_fr_account_invoice_import_simple_pdf/__manifest__.py
odoo/addons/l10n_fr_account_invoice_import_simple_pdf/i18n/fr.po
odoo/addons/l10n_fr_account_invoice_import_simple_pdf/i18n/l10n_fr_account_invoice_import_simple_pdf.pot
odoo/addons/l10n_fr_account_invoice_import_simple_pdf/readme/CONTRIBUTORS.rst
odoo/addons/l10n_fr_account_invoice_import_simple_pdf/readme/DESCRIPTION.rst
odoo/addons/l10n_fr_account_invoice_import_simple_pdf/static/description/icon.png
odoo/addons/l10n_fr_account_invoice_import_simple_pdf/static/description/index.html
odoo/addons/l10n_fr_account_invoice_import_simple_pdf/wizards/__init__.py
odoo/addons/l10n_fr_account_invoice_import_simple_pdf/wizards/account_invoice_import.py
odoo14_addon_l10n_fr_account_invoice_import_simple_pdf-14.0.1.0.1.dev6.dist-info/METADATA
odoo14_addon_l10n_fr_account_invoice_import_simple_pdf-14.0.1.0.1.dev6.dist-info/WHEEL
odoo14_addon_l10n_fr_account_invoice_import_simple_pdf-14.0.1.0.1.dev6.dist-info/top_level.txt
odoo14_addon_l10n_fr_account_invoice_import_simple_pdf-14.0.1.0.1.dev6.dist-info/RECORD
